toml_decouple/__init__.py
toml_decouple/helpers.py
toml_decouple/parsers.py
toml_decouple/py.typed
toml_decouple/settings.py
toml_decouple/toml_types.py
toml_decouple-0.6.0.dist-info/WHEEL
toml_decouple-0.6.0.dist-info/METADATA
toml_decouple-0.6.0.dist-info/RECORD
