Metadata-Version: 2.3
Name: toml-decouple
Version: 0.6.0
Summary: TOML powered .env file configuration and secrets
Author: Baptiste Darthenay
Author-email: Baptiste Darthenay <baptiste.darthenay@gmail.com>
Classifier: Development Status :: 4 - Beta
Classifier: Framework :: aiohttp
Classifier: Framework :: Django
Classifier: Framework :: Flask
Classifier: Framework :: Wagtail
Classifier: Intended Audience :: Developers
Classifier: License :: OSI Approved :: GNU General Public License v3 or later (GPLv3+)
Classifier: Natural Language :: English
Classifier: Operating System :: OS Independent
Classifier: Programming Language :: Python
Classifier: Programming Language :: Python :: 3
Classifier: Programming Language :: Python :: 3.12
Classifier: Programming Language :: Python :: 3.13
Classifier: Topic :: Software Development
Classifier: Topic :: Utilities
Classifier: Typing :: Typed
Requires-Dist: dj-database-url>=3.0.0 ; extra == 'db'
Requires-Python: >=3.12
Provides-Extra: db
